netbox_device_map/__init__.py
netbox_device_map/forms.py
netbox_device_map/geographical_map.py
netbox_device_map/helpers.py
netbox_device_map/navigation.py
netbox_device_map/settings.py
netbox_device_map/urls.py
netbox_device_map/views.py
netbox_device_map/static/netbox_device_map/style.css
netbox_device_map/static/netbox_device_map/js/map.js
netbox_device_map/static/netbox_device_map/js/svg-icon.js
netbox_device_map/static/netbox_device_map/leaflet/leaflet-src.esm.js
netbox_device_map/static/netbox_device_map/leaflet/leaflet-src.esm.js.map
netbox_device_map/static/netbox_device_map/leaflet/leaflet-src.js
netbox_device_map/static/netbox_device_map/leaflet/leaflet-src.js.map
netbox_device_map/static/netbox_device_map/leaflet/leaflet.css
netbox_device_map/static/netbox_device_map/leaflet/leaflet.js
netbox_device_map/static/netbox_device_map/leaflet/leaflet.js.map
netbox_device_map/static/netbox_device_map/leaflet/images/layers-2x.png
netbox_device_map/static/netbox_device_map/leaflet/images/layers.png
netbox_device_map/static/netbox_device_map/leaflet/images/marker-icon-2x.png
netbox_device_map/static/netbox_device_map/leaflet/images/marker-icon.png
netbox_device_map/static/netbox_device_map/leaflet/images/marker-shadow.png
netbox_device_map/static/netbox_device_map/leaflet/v1.7.1/leaflet-src.esm.js
netbox_device_map/static/netbox_device_map/leaflet/v1.7.1/leaflet-src.esm.js.map
netbox_device_map/static/netbox_device_map/leaflet/v1.7.1/leaflet-src.js
netbox_device_map/static/netbox_device_map/leaflet/v1.7.1/leaflet-src.js.map
netbox_device_map/static/netbox_device_map/leaflet/v1.7.1/leaflet.css
netbox_device_map/static/netbox_device_map/leaflet/v1.7.1/leaflet.js
netbox_device_map/static/netbox_device_map/leaflet/v1.7.1/leaflet.js.map
netbox_device_map/static/netbox_device_map/leaflet/v1.7.1/images/layers-2x.png
netbox_device_map/static/netbox_device_map/leaflet/v1.7.1/images/layers.png
netbox_plugin_device_map-0.1.3.dist-info/LICENSE
netbox_plugin_device_map-0.1.3.dist-info/METADATA
netbox_plugin_device_map-0.1.3.dist-info/WHEEL
netbox_plugin_device_map-0.1.3.dist-info/top_level.txt
netbox_plugin_device_map-0.1.3.dist-info/RECORD
