Metadata-Version: 2.1
Name: netbox-plugin-device-map
Version: 0.1.3
Summary: A simple device map with filter criteria
Home-page: https://github.com/drygdryg/netbox-plugin-device-map
Download-URL: https://github.com/drygdryg/netbox-plugin-device-map/archive/v0.1.3.zip
Author: Victor Golovanenko
Author-email: drygdryg2014@yandex.com
License: MIT
Classifier: Environment :: Plugins
Classifier: Environment :: Web Environment
Classifier: Framework :: Django
Classifier: License :: OSI Approved :: MIT License
Classifier: Topic :: System :: Networking
Classifier: Topic :: System :: Systems Administration
Requires-Python: >3.9
License-File: LICENSE
